woeboost/__init__.py
woeboost/classifier.py
woeboost/explainer.py
woeboost/learner.py
woeboost-1.1.0.dist-info/licenses/LICENSE.md
woeboost-1.1.0.dist-info/METADATA
woeboost-1.1.0.dist-info/WHEEL
woeboost-1.1.0.dist-info/top_level.txt
woeboost-1.1.0.dist-info/RECORD
