Metadata-Version: 2.4
Name: woeboost
Version: 1.1.0
Summary: WoeBoost: Weight of Evidence (WOE) Gradient Boosting
Author-email: xRiskLab <contact@xrisklab.ai>
License-Expression: MIT
Project-URL: Repository, https://github.com/xRiskLab/woeboost
Project-URL: Homepage, https://github.com/xRiskLab/woeboost
Keywords: weight of evidence,gradient boosting,scoring,classification
Classifier: Development Status :: 5 - Production/Stable
Classifier: Intended Audience :: Developers
Classifier: Intended Audience :: Science/Research
Classifier: Programming Language :: Python :: 3
Classifier: Programming Language :: Python :: 3.9
Classifier: Programming Language :: Python :: 3.10
Classifier: Programming Language :: Python :: 3.11
Classifier: Topic :: Scientific/Engineering :: Artificial Intelligence
Requires-Python: >=3.9
License-File: LICENSE.md
Requires-Dist: matplotlib<4.0.0,>=3.8.0
Requires-Dist: numpy<3.0.0,>=1.19.5
Requires-Dist: pandas<3.0.0,>=2.0.0
Requires-Dist: scikit-learn<2.0.0,>=1.3.0
Requires-Dist: rich<14.0.0,>=13.7.1
Requires-Dist: cmap<1.0.0,>=0.4.0
Requires-Dist: pydocstyle<7.0.0,>=6.3.0
Provides-Extra: freethreaded
Requires-Dist: numpy>=2.0.0; extra == "freethreaded"
Requires-Dist: pandas>=2.0.0; extra == "freethreaded"
Requires-Dist: scikit-learn>=1.3.0; extra == "freethreaded"
Requires-Dist: rich<14.0.0,>=13.7.1; extra == "freethreaded"
Dynamic: license-file
